{
  "env": "development",
  "port": 3000,
  "node": {
    "url": "https://nodes.lto.network"
  },
  "log": {
    "level": "debug"
  },
  "starting_block": 1972742,
  "transaction": {
    "indexing": false
  },
  "anchor": {
    "indexing": "none"
  },
  "association": {
    "indexing": "none"
  },
  "stats": {
    "operations": true,
    "transactions": true,
    "supply": false
  },
  "identity": {
    "indexing": false
  },
  "cross_chain": {
    "eip155": {
      "indexing": false
    }
  }
}
